{
  "Banking & Finance": ["RBI Policy", "Banking Regulation", "NBFC Policy", "Digital Payments", "FDI in Finance", "Taxation", "GST", "Budget", "Fiscal Policy"],
  "Defence": ["Procurement", "FDI in Defence", "Indigenous Manufacturing", "Make in India Defence", "Arms Export"],
  "Energy": ["Nuclear Energy", "Oil & Gas", "Coal & Mining", "Power Distribution", "Energy Policy", "LNG", "Gas Pipeline"],
  "Renewable Energy": ["Solar Policy", "Wind Energy", "Green Hydrogen", "EV & Battery", "Carbon Credits", "Clean Energy Transition"],
  "Infrastructure": ["Roads & Highways", "Railways", "Ports & Shipping", "Smart Cities", "Urban Development", "Water Supply"],
  "Real Estate & Housing": ["Housing Policy", "PMAY", "RERA", "Urban Planning"],
  "Agriculture": ["MSP & Procurement", "Subsidies", "Export Policy", "Fertilizer Policy", "Irrigation", "Farm Reforms"],
  "Healthcare": ["Pharma Policy", "Medical Devices", "Drug Pricing", "Hospital Regulation", "AYUSH", "Vaccine Policy"],
  "Technology": ["Digital India", "Semiconductors", "Data Privacy", "Cybersecurity", "AI Policy", "Startup Policy"],
  "Telecom": ["Spectrum Allocation", "5G Rollout", "Broadband", "BSNL Reform", "Satellite Communication"],
  "Metals & Mining": ["Steel Policy", "Mining Auction", "Metal Export/Import", "Coal Allocation", "Critical Minerals"],
  "Chemicals & Fertilizers": ["Chemical Policy", "Fertilizer Subsidy", "PLI Chemicals", "Agrochemicals"],
  "Aviation": ["Airline Policy", "Airport Development", "UDAN Scheme", "MRO Policy"],
  "Textiles & Apparel": ["Textile PLI", "Cotton Policy", "Export Incentives", "Technical Textiles"],
  "Automobile & EV": ["Auto Policy", "EV Subsidies", "FAME Scheme", "Scrappage Policy", "Emission Norms"],
  "Trade & Commerce": ["Export Policy", "Import Duties", "Anti-Dumping", "FTA Agreements", "PLI Schemes"],
  "Regulation": ["SEBI Regulation", "CCI Decisions", "M&A Approvals", "Listing Rules", "Corporate Governance"],
  "Insurance": ["Insurance Regulation", "FDI in Insurance", "IRDAI Policy", "Crop Insurance"],
  "Space & Satellite": ["ISRO Missions", "Private Space", "Satellite Policy", "Space Commerce"],
  "Environment & ESG": ["Carbon Policy", "Pollution Norms", "Green Bonds", "ESG Regulation", "Forest Clearance"],
  "Education & Skill": ["Education Policy", "Skill Development", "Digital Education"],
  "Disinvestment": ["PSU Disinvestment", "Strategic Sale", "OFS", "IPO of PSU"],
  "Labour & Employment": ["Labour Reforms", "Wage Policy", "Social Security", "Gig Economy"],
  "Policy & Planning": ["Cabinet Decisions", "NITI Aayog", "Economic Survey", "GDP & Growth", "Reform Agenda"],
  "Consumer & Retail": ["Consumer Protection", "E-Commerce Policy", "Food Safety", "FMCG Regulation"]
}
